timbrel/__init__.py
timbrel/admin.py
timbrel/apps.py
timbrel/at.py
timbrel/backends.py
timbrel/base.py
timbrel/filters.py
timbrel/forms.py
timbrel/gmaps.py
timbrel/inlines.py
timbrel/models.py
timbrel/paginators.py
timbrel/permissions.py
timbrel/serializers.py
timbrel/tasks.py
timbrel/tests.py
timbrel/urls.py
timbrel/utils.py
timbrel/views.py
timbrel/management/commands/seed_pages.py
timbrel/management/commands/seed_tags.py
timbrel/migrations/0001_initial.py
timbrel/migrations/0002_alter_order_customer.py
timbrel/migrations/__init__.py
timbrel-0.1.25.dist-info/LICENSE
timbrel-0.1.25.dist-info/METADATA
timbrel-0.1.25.dist-info/WHEEL
timbrel-0.1.25.dist-info/top_level.txt
timbrel-0.1.25.dist-info/RECORD
