Metadata-Version: 2.1
Name: timbrel
Version: 0.1.25
Summary: timbrel is a Django app to provide the basic framework for ecommerce.
Author-email: Kigathi Chege <chegekigathi@gmail.com>
Project-URL: Homepage, https://www.example.com/
Classifier: Environment :: Web Environment
Classifier: Framework :: Django
Classifier: Framework :: Django :: 5.1
Classifier: Intended Audience :: Developers
Classifier: License :: OSI Approved :: BSD License
Classifier: Operating System :: OS Independent
Classifier: Programming Language :: Python
Classifier: Programming Language :: Python :: 3
Classifier: Programming Language :: Python :: 3 :: Only
Classifier: Programming Language :: Python :: 3.10
Classifier: Programming Language :: Python :: 3.11
Classifier: Programming Language :: Python :: 3.12
Classifier: Programming Language :: Python :: 3.13
Classifier: Topic :: Internet :: WWW/HTTP
Classifier: Topic :: Internet :: WWW/HTTP :: Dynamic Content
Requires-Python: >=3.10
License-File: LICENSE
Requires-Dist: django>=5.1
Requires-Dist: africastalking>=1.2.9
Requires-Dist: celery>=5.4.0
Requires-Dist: django-cities-light>=3.10.1
Requires-Dist: django-unfold>=0.43.0
Requires-Dist: djangorestframework>=3.15.2
Requires-Dist: inflect>=7.4.0
Requires-Dist: django-simple-history>=3.7.0
Requires-Dist: django-phonenumber-field>=8.0.0
Requires-Dist: django-import-export>=4.3.3
Requires-Dist: django-filter>=24.3
